{
  "schema_version": 2,
  "project": {
    "name": "unuvault",
    "manifest": "scripts/testing/test-runner.sh"
  },
  "surfaces": [
    {
      "name": "lint-runner",
      "type": "profile",
      "target": "lint-runner",
      "domain": "testing",
      "visibility": "human-and-machine"
    },
    {
      "name": "test-runner",
      "type": "profile",
      "target": "test-runner",
      "domain": "testing",
      "visibility": "human-and-machine"
    },
    {
      "name": "ios-test-runner",
      "type": "profile",
      "target": "ios-test-runner",
      "domain": "testing",
      "visibility": "human-and-machine"
    }
  ],
  "entrypoints": {
    "ios_test_runner": "scripts/testing/run-ios.sh",
    "lint_runner": "scripts/testing/lint-runner.sh",
    "test_runner": "scripts/testing/test-runner.sh"
  }
}
